{"stats":{"minecraft:killed_by":{"minecraft:player":3,"minecraft:zombified_piglin":8,"minecraft:wither_skeleton":1,"minecraft:skeleton":3,"minecraft:creeper":3,"minecraft:phantom":1,"minecraft:zombie":3,"theabyss:magical_deer":1,"theabyss:end_spider":2},"minecraft:mined":{"minecraft:glass_pane":2,"theabyss:bog_log_fungi":1,"minecraft:torch":1,"minecraft:grass_block":1,"theabyss:bog_vine":1,"minecraft:tall_grass":1,"biomesoplenty:dead_branch":1,"minecraft:fire":2,"minecraft:grass":4,"theabyss:loran_flower":16,"lucky:lucky_block":1},"minecraft:picked_up":{"iceandfire:witherbone":1,"minecraft:leather_leggings":1,"minecraft:potion":1,"enigmaticlegacy:tattered_tome":2,"minecraft:shield":1,"artifacts:cloud_in_a_bottle":1,"minecraft:dirt":1,"artifacts:feral_claws":1,"artifacts:shock_pendant":1,"minecraft:bone":20,"mutantmore:mutant_wither_skeleton_skull":1,"minecraft:diamond_leggings":1,"minecraft:wheat_seeds":5,"minecraft:diamond_helmet":1,"theabyss:loran":29,"magistuarmory:rustedchainmail_chestplate":1,"cavesandcliffs:amethyst_block":17,"minecraft:torch":2,"epicfight:skillbook":2,"minecraft:porkchop":4,"minecraft:redstone":1,"artifacts:lucky_scarf":1,"minecraft:diamond_chestplate":1,"minecraft:arrow":27,"minecraft:rotten_flesh":9,"enigmaticlegacy:cursed_ring":1,"artifacts:golden_hook":1,"magistuarmory:rusted_bastardsword":1,"artifacts:crystal_heart":1,"magistuarmory:rustedcrusader_boots":1,"minecraft:diamond_boots":1,"artifacts:running_shoes":1,"xreliquary:rib_bone":5,"minecraft:mutton":1,"minecraft:white_wool":2},"minecraft:killed":{"minecraft:pig":1,"minecraft:witch":1,"alexsmobs:raccoon":1,"minecraft:spider":1,"minecraft:phantom":1,"minecraft:sheep":1,"minecraft:skeleton":20,"minecraft:zombie":19,"minecraft:wither_skeleton":7},"minecraft:used":{"epicfight:skillbook":2,"useless_sword:lapis_lazuli_sword":9,"minecraft:shield":15,"minecraft:torch":1,"minecraft:dirt":1,"mowziesmobs:wrought_axe":237,"minecraft:bread":2,"minecraft:diamond_sword":46},"minecraft:dropped":{"minecraft:porkchop":4,"minecraft:wheat_seeds":1,"minecraft:lapis_lazuli":7,"cavesandcliffs:amethyst_block":17,"artifacts:shock_pendant":1,"enigmaticlegacy:tattered_tome":2,"theabyss:loran":15,"enigmaticlegacy:cursed_ring":1,"mca:book_romance":1,"minecraft:torch":1,"minecraft:mutton":1,"magistuarmory:rusted_bastardsword":1,"magistuarmory:rustedchainmail_chestplate":1,"minecraft:white_wool":2,"epicfight:skillbook":1,"theabyss:guide_book":1,"minecraft:bone":2,"minecraft:redstone":1},"minecraft:crafted":{"useless_sword:emerald_stick":2,"useless_sword:lapis_lazuli_sword":1,"minecraft:lapis_block":2},"minecraft:custom":{"minecraft:mob_kills":55,"minecraft:interact_with_crafting_table":1,"minecraft:open_barrel":4,"minecraft:play_one_minute":100268,"minecraft:leave_game":1,"minecraft:time_since_death":183,"minecraft:sleep_in_bed":2,"minecraft:climb_one_cm":564,"minecraft:time_since_rest":243,"minecraft:waystone_activated":1,"minecraft:sprint_one_cm":354786,"minecraft:damage_taken":5085,"minecraft:walk_one_cm":172023,"minecraft:damage_blocked_by_shield":2650,"minecraft:drop":23,"minecraft:damage_dealt":10746,"minecraft:swim_one_cm":30167,"minecraft:fly_one_cm":474117,"minecraft:open_chest":13,"minecraft:crouch_one_cm":7599,"minecraft:deaths":29,"minecraft:sneak_time":2172,"minecraft:walk_under_water_one_cm":4648,"minecraft:jump":1912,"minecraft:interact_with_blast_furnace":1,"minecraft:walk_on_water_one_cm":6126,"minecraft:fall_one_cm":36467}},"DataVersion":2586}